html2phpbbcode/__init__.py
html2phpbbcode/parser.py
html2phpbbcode/validators.py
html2phpbbcode/data/defaults.conf
html2phpbbcode-0.1.4.dist-info/METADATA
html2phpbbcode-0.1.4.dist-info/RECORD
html2phpbbcode-0.1.4.dist-info/WHEEL
html2phpbbcode-0.1.4.dist-info/top_level.txt
