Metadata-Version: 2.1
Name: html2phpbbcode
Version: 0.1.4
Summary: HTML to phpBB-compatible BBCode converter
Home-page: https://github.com/tdiam/html2phpbbcode
Author: Theodoros Diamantidis
Author-email: diamaltho@gmail.com
License: BSD
Platform: UNKNOWN
Classifier: Topic :: Utilities
Classifier: Topic :: Text Processing :: Markup :: HTML
Classifier: Topic :: Software Development :: Libraries :: Python Modules
Classifier: Development Status :: 2 - Pre-Alpha
Classifier: Intended Audience :: Developers
Classifier: Operating System :: OS Independent
Classifier: License :: OSI Approved :: BSD License
Classifier: Programming Language :: Python :: 3.5
Classifier: Programming Language :: Python :: 3.6
Classifier: Programming Language :: Python :: 3.7
